COPYING
MANIFEST.in
README.rst
ogrdifference
ogrintersection
setup.py
ogrkit/__init__.py
ogrkit/cli.py
ogrkit/utils.py
ogrkit.egg-info/PKG-INFO
ogrkit.egg-info/SOURCES.txt
ogrkit.egg-info/dependency_links.txt
ogrkit.egg-info/requires.txt
ogrkit.egg-info/top_level.txt
ogrkit/utilities/__init__.py
ogrkit/utilities/difference.py
ogrkit/utilities/intersection.py