Metadata-Version: 1.0
Name: ogrkit
Version: 0.0.2
Summary: A suite of command-line utilities implementing basic geometric operations. 
Home-page: http://blog.apps.chicagotribune.com/
Author: Christopher Groskopf
Author-email: staringmonkey@gmail.com
License: MIT
Platform: UNKNOWN
